Single-Cycle/rtl/alu.sv
//////////////////////////////////////////////////////////////// 
// Engineer: Evan Apinis
// 
// Module Name: alu.sv
// Project Name: RV32I 
// Description: 
// 
// ALU module for a RV32I CPU supporting the entire
// base instruction set.
//
// Revision 0.01 - File Created
// 
////////////////////////////////////////////////////////////////
`timescale 1ns / 1ps

module alu #(
  parameter DWIDTH = 32
)(
  input   logic [DWIDTH-1:0]  ALU_In_A, //Operand A
  input   logic [DWIDTH-1:0]  ALU_In_B, //Operand B
  input   logic [3:0]         ALU_OP,   //ALU Opcode
  output  logic [DWIDTH-1:0]  ALU_Out,  //ALU Result
  output  logic               ALU_Zero_Flag
);

/*
-----------------------------------------------
|ALU_Sel |   ALU_OPERATION              |
-----------------------------------------------
|  0000  |   ALU_Out = A + B;           |  ADD
-----------------------------------------------
|  0001  |   ALU_Out = A - B;           |  SUB
-----------------------------------------------
|  0010  |   ALU_Out = A << B;          |  SLL
-----------------------------------------------
|  0011  |   ALU_Out = (A < B) ? 1 : 0; |  SLT
-----------------------------------------------
|  0100  |   ALU_Out = (A < B) ? 1 : 0; |  SLTU
-----------------------------------------------
|  0101  |   ALU_Out = A ^ B;           |  XOR
-----------------------------------------------
|  0110  |   ALU_Out = A >> B;          |  SRL
-----------------------------------------------
|  0111  |   ALU_Out = A >>> B;         |  SRA
-----------------------------------------------
|  1000  |   ALU_Out = A | B;           |  OR
-----------------------------------------------
|  1001  |   ALU_Out = A & B;           |  AND
-----------------------------------------------
*/

////////////////////////////////////////////////////////////////
////////////////////////   Parameters   ////////////////////////
////////////////////////////////////////////////////////////////

//Local parameters for ALU decode from control logic
localparam ADD  = 4'b0000;
localparam SUB  = 4'b0001;
localparam SLL  = 4'b0010;
localparam SLT  = 4'b0011;
localparam SLTU = 4'b0100;
localparam XOR  = 4'b0101;
localparam SRL  = 4'b0110;
localparam SRA  = 4'b0111;
localparam OR   = 4'b1000;
localparam AND  = 4'b1001;
localparam MULT = 4'b1010;

////////////////////////////////////////////////////////////////
///////////////////////   Internal Net   ///////////////////////
////////////////////////////////////////////////////////////////

logic [DWIDTH-1:0] mul_div_low;
logic [DWIDTH-1:0] mul_div_upper;

////////////////////////////////////////////////////////////////
///////////////////////   Module Logic   ///////////////////////
////////////////////////////////////////////////////////////////

always@(*) begin
  case(ALU_OP)
    ADD:  ALU_Out = ALU_In_A + ALU_In_B; //add
    SUB:  ALU_Out = ALU_In_A - ALU_In_B; //subtract
    SLL:  ALU_Out = ALU_In_A << ALU_In_B; //logical left shift
    SLT:  ALU_Out = ($signed(ALU_In_A) < $signed(ALU_In_B)) ? 1 : '0; //signed less than
    SLTU: ALU_Out = (ALU_In_A < ALU_In_B) ? 1 : '0; //Unsigned set on less then
    XOR:  ALU_Out = ALU_In_A ^ ALU_In_B; //xor
    SRL:  ALU_Out = ALU_In_A >> ALU_In_B; //shift logic right
    SRA:  ALU_Out = $signed(ALU_In_A) >>> ALU_In_B; //signed shift logic right
    OR:   ALU_Out = ALU_In_A | ALU_In_B; //or
    AND:  ALU_Out = ALU_In_A & ALU_In_B; //and
    default: begin
      ALU_Out = 32'b0; //default add
    end
  endcase

  ALU_Zero_Flag = (ALU_Out == 32'b0) ? 1'b1 : 1'b0; // set on zero
end

////////////////////////////////////////////////////////////////
//////////////////   Instantiation Template   //////////////////
////////////////////////////////////////////////////////////////
/*
alu #(
  .DWIDTH(32)
)
alu
(
  .ALU_In_A(),
  .ALU_In_B(),
  .ALU_OP(),
  .ALU_Out(),
  .ALU_Zero_Flag()
);
*/

endmodule

Single-Cycle/sim/alu/alu_tb.sv
`timescale 1ns / 1ps

module alu_tb (
);

////////////////////////////////////////////////////////////////
////////////////////////   Parameters   ////////////////////////
////////////////////////////////////////////////////////////////

parameter SEED = 5;

////////////////////////////////////////////////////////////////
///////////////////////   Internal Net   ///////////////////////
////////////////////////////////////////////////////////////////

// DUT Nets
reg   [31:0]  ALU_In_A;
reg   [31:0]  ALU_In_B;
reg   [3:0]   ALU_OP;
wire  [31:0]  ALU_Out;
wire          ALU_Zero_Flag;

// Expected outputs
reg   [31:0]  Expected_ALU_Out;
reg           Expected_ALU_Zero_Flag;
integer       Test_Failed;

////////////////////////////////////////////////////////////////
//////////////////////   Instantiations   //////////////////////
////////////////////////////////////////////////////////////////

alu #(
  .DWIDTH(32)
)
DUT
(
  .ALU_In_A(ALU_In_A),
  .ALU_In_B(ALU_In_B),
  .ALU_OP(ALU_OP),
  .ALU_Out(ALU_Out),
  .ALU_Zero_Flag(ALU_Zero_Flag)
);

////////////////////////////////////////////////////////////////
///////////////////////   Task Definitions   ///////////////////
////////////////////////////////////////////////////////////////

task compute_expected_output;
  input   [31:0]  a, b;
  input   [3:0]   op;
  output  [31:0]  result;
  output          zero_flag;
  
  begin
    case (op)
      4'b0000:  result = a + b;
      4'b0001:  result = a - b;
      4'b0010:  result = a << b;
      4'b0011:  result = ($signed(a) < $signed(b)) ? 32'b1 : 32'b0;
      4'b0100:  result = (a < b) ? 32'b1 : 32'b0;
      4'b0101:  result = a ^ b;
      4'b0110:  result = a >> b;
      4'b0111:  result = $signed(a) >>> b;
      4'b1000:  result = a | b;
      4'b1001:  result = a & b;
      default:  result = 0;
    endcase
    
    zero_flag = (result == 0);
  end

endtask

////////////////////////////////////////////////////////////////
///////////////////////   Module Logic   ///////////////////////
////////////////////////////////////////////////////////////////

initial begin
  $dumpfile("alu.vcd");
  $dumpvars(0, alu_tb);
  
  Test_Failed = 0;
  //$random(SEED);
  
  repeat(1000) begin
    ALU_In_A = $unsigned($random);
    ALU_In_B = $unsigned($random);
    ALU_OP   = $unsigned($random) % 16;
    
    #5;
    
    // Compute expected outputs
    compute_expected_output(ALU_In_A, ALU_In_B, ALU_OP, Expected_ALU_Out, Expected_ALU_Zero_Flag);
    
    // Compare DUT output with expected output
    if (ALU_Out !== Expected_ALU_Out || ALU_Zero_Flag !== Expected_ALU_Zero_Flag) begin
      $display("Test Failed at time %0t", $time);
      $display("Inputs: ALU_In_A = %h, ALU_In_B = %h, ALU_OP = %b", ALU_In_A, ALU_In_B, ALU_OP);
      $display("DUT Output: ALU_Out = %h, ALU_Zero_Flag = %b", ALU_Out, ALU_Zero_Flag);
      $display("Expected: ALU_Out = %h, ALU_Zero_Flag = %b", Expected_ALU_Out, Expected_ALU_Zero_Flag);
      Test_Failed = 1;
    end
  end
  
  if (!Test_Failed) begin
    $display("All tests passed!");
  end else begin
    $display("Some tests failed. Check the log for details.");
  end
  
  $finish;
end

endmodule

Single-Cycle/sim/alu/alu.vcd
$date
	Fri Dec 13 23:32:35 2024
$end
$version
	Icarus Verilog
$end
$timescale
	1ps
$end
$scope module alu_tb $end
$var wire 1 ! ALU_Zero_Flag $end
$var wire 32 " ALU_Out [31:0] $end
$var reg 32 # ALU_In_A [31:0] $end
$var reg 32 $ ALU_In_B [31:0] $end
$var reg 4 % ALU_OP [3:0] $end
$var reg 32 & Expected_ALU_Out [31:0] $end
$var reg 1 ' Expected_ALU_Zero_Flag $end
$var integer 32 ( Test_Failed [31:0] $end
$scope module DUT $end
$var wire 32 ) ALU_In_A [31:0] $end
$var wire 32 * ALU_In_B [31:0] $end
$var wire 4 + ALU_OP [3:0] $end
$var reg 32 , ALU_Out [31:0] $end
$var reg 1 ! ALU_Zero_Flag $end
$upscope $end
$scope task compute_expected_output $end
$var reg 32 - a [31:0] $end
$var reg 32 . b [31:0] $end
$var reg 4 / op [3:0] $end
$var reg 32 0 result [31:0] $end
$var reg 1 1 zero_flag $end
$upscope $end
$upscope $end
$enddefinitions $end
#0
$dumpvars
x1
bx 0
bx /
bx .
bx -
b10001010000000000 ,
b1001 +
b11000000100010010101111010000001 *
b10010000101010011010100100100 )
b0 (
x'
bx &
b1001 %
b11000000100010010101111010000001 $
b10010000101010011010100100100 #
b10001010000000000 "
0!
$end
#5000
1!
b0 "
b0 ,
b1101 %
b1101 +
b110101110010111101100001101 $
b110101110010111101100001101 *
b10110001111100000101011001100011 #
b10110001111100000101011001100011 )
0'
b10001010000000000 &
01
b10001010000000000 0
b1001 /
b11000000100010010101111010000001 .
b10010000101010011010100100100 -
#10000
0!
b101001100010110011001001010011 "
b101001100010110011001001010011 ,
b1 %
b1 +
b10001001001101110101001000010010 $
b10001001001101110101001000010010 *
b10110010110000101000010001100101 #
b10110010110000101000010001100101 )
1'
b0 &
11
b0 0
b1101 /
b110101110010111101100001101 .
b10110001111100000101011001100011 -
#15000
1!
b0 "
b0 ,
b1101 %
b1101 +
b111011001000111111000101110110 $
b111011001000111111000101110110 *
b110110101111100110100001101 #
b110110101111100110100001101 )
0'
b101001100010110011001001010011 &
01
b101001100010110011001001010011 0
b1 /
b10001001001101110101001000010010 .
b10110010110000101000010001100101 -
#20000
0!
b1000110000001000101011110001100 "
b1000110000001000101011110001100 ,
b1001 %
b1001 +
b1000110001011011111011110001100 $
b1000110001011011111011110001100 *
b1110110110101000101011111101101 #
b1110110110101000101011111101101 )
1'
b0 &
11
b0 0
b1101 /
b111011001000111111000101110110 .
b110110101111100110100001101 -
#25000
1!
b0 "
b0 ,
b1010 %
b1010 +
b11100010111101111000010011000101 $
b11100010111101111000010011000101 *
b11100011001101110010010011000110 #
b11100011001101110010010011000110 )
0'
b1000110000001000101011110001100 &
01
b1000110000001000101011110001100 0
b1001 /
b1000110001011011111011110001100 .
b1110110110101000101011111101101 -
#30000
b10 %
b10 +
b10111011110100100111001001110111 $
b10111011110100100111001001110111 *
b1110010101011111111011111100101 #
b1110010101011111111011111100101 )
1'
b0 &
11
b0 0
b1010 /
b11100010111101111000010011000101 .
b11100011001101110010010011000110 -
#35000
b1110 %
b1110 +
b1111001001100000110100111110010 $
b1111001001100000110100111110010 *
b1000111111011001101101110001111 #
b1000111111011001101101110001111 )
b10 /
b10111011110100100111001001110111 .
b1110010101011111111011111100101 -
#40000
b1100 %
b1100 +
b11100010110010100100111011000101 $
b11100010110010100100111011000101 *
b11110100000000000111101011101000 #
b11110100000000000111101011101000 )
b1110 /
b1111001001100000110100111110010 .
b1000111111011001101101110001111 -
#45000
0!
b1001000001001010111000010010000 "
b1001000001001010111000010010000 ,
b101 %
b101 +
b10010110101010110101100000101101 $
b10010110101010110101100000101101 *
b11011110100011100010100010111101 #
b11011110100011100010100010111101 )
b1100 /
b11100010110010100100111011000101 .
b11110100000000000111101011101000 -
#50000
b10110111011000101110100101101101 "
b10110111011000101110100101101101 ,
b0 %
b0 +
b101011100111000011100001010 $
b101011100111000011100001010 *
b10110001111011110110001001100011 #
b10110001111011110110001001100011 )
0'
b1001000001001010111000010010000 &
01
b1001000001001010111000010010000 0
b101 /
b10010110101010110101100000101101 .
b11011110100011100010100010111101 -
#55000
1!
b0 "
b0 ,
b1101 %
b1101 +
b1010101011110000100010110101010 $
b1010101011110000100010110101010 *
b10000011001000010000100100000 #
b10000011001000010000100100000 )
b10110111011000101110100101101101 &
b10110111011000101110100101101101 0
b0 /
b101011100111000011100001010 .
b10110001111011110110001001100011 -
#60000
b10001001100000111011100000010011 $
b10001001100000111011100000010011 *
b11001011001000000011111010010110 #
b11001011001000000011111010010110 )
1'
b0 &
11
b0 0
b1101 /
b1010101011110000100010110101010 .
b10000011001000010000100100000 -
#65000
0!
b10011100001110000000101100111000 "
b10011100001110000000101100111000 ,
b101 %
b101 +
b110101100111111101110101101011 $
b110101100111111101110101101011 *
b10101001101001111101011001010011 #
b10101001101001111101011001010011 )
b10001001100000111011100000010011 .
b11001011001000000011111010010110 -
#70000
1!
b0 "
b0 ,
b1101 %
b1101 +
b11010111010101100011111010101110 $
b11010111010101100011111010101110 *
b10000001000101110100101000000010 #
b10000001000101110100101000000010 )
0'
b10011100001110000000101100111000 &
01
b10011100001110000000101100111000 0
b101 /
b110101100111111101110101101011 .
b10101001101001111101011001010011 -
#75000
b1010 %
b1010 +
b10001100001000100100100100011 $
b10001100001000100100100100011 *
b11100111110001010111001011001111 #
b11100111110001010111001011001111 )
1'
b0 &
11
b0 0
b1101 /
b11010111010101100011111010101110 .
b10000001000101110100101000000010 -
#80000
b10 %
b10 +
b10011110001100010100110000111100 $
b10011110001100010100110000111100 *
b11100101011100110000101011001010 #
b11100101011100110000101011001010 )
b1010 /
b10001100001000100100100100011 .
b11100111110001010111001011001111 -
#85000
0!
b1100101111011101111001111001011 "
b1100101111011101111001111001011 ,
b1000 %
b1000 +
b100000110001001011001101000001 $
b100000110001001011001101000001 *
b1000101001011100110000110001010 #
b1000101001011100110000110001010 )
b10 /
b10011110001100010100110000111100 .
b11100101011100110000101011001010 -
#90000
1!
b0 "
b0 ,
b1011 %
b1011 +
b11000100100010100001001010001001 $
b11000100100010100001001010001001 *
b111100001000001111001101111000 #
b111100001000001111001101111000 )
0'
b1100101111011101111001111001011 &
01
b1100101111011101111001111001011 0
b1000 /
b100000110001001011001101000001 .
b1000101001011100110000110001010 -
#95000
b1110 %
b1110 +
b1100011010010111111100111000110 $
b1100011010010111111100111000110 *
b1011011000000100110010110110110 #
b1011011000000100110010110110110 )
1'
b0 &
11
b0 0
b1011 /
b11000100100010100001001010001001 .
b111100001000001111001101111000 -
#100000
b1011 %
b1011 +
b10101000011111101110100101010 $
b10101000011111101110100101010 *
b11011110011101010000001010111100 #
b11011110011101010000001010111100 )
b1110 /
b1100011010010111111100111000110 .
b1011011000000100110010110110110 -
#105000
b1111 %
b1111 +
b1000010111100100100000110000101 $
b1000010111100100100000110000101 *
b10111000100101111011111001110001 #
b10111000100101111011111001110001 )
b1011 /
b10101000011111101110100101010 .
b11011110011101010000001010111100 -
#110000
b1110 %
b1110 +
b11101000001100011001100111010 $
b11101000001100011001100111010 *
b10011101110011000110000000111011 #
b10011101110011000110000000111011 )
b1111 /
b1000010111100100100000110000101 .
b10111000100101111011111001110001 -
#115000
0!
b1000100010000000101100010001 "
b1000100010000000101100010001 ,
b1001 %
b1001 +
b1111000110110011001101111110001 $
b1111000110110011001101111110001 *
b1010101010100100101100010101 #
b1010101010100100101100010101 )
b1110 /
b11101000001100011001100111010 .
b10011101110011000110000000111011 -
#120000
1!
b0 "
b0 ,
b1111 %
b1111 +
b100110001101011111101101001100 $
b100110001101011111101101001100 *
b110001001000110000011101100010 #
b110001001000110000011101100010 )
0'
b1000100010000000101100010001 &
01
b1000100010000000101100010001 0
b1001 /
b1111000110110011001101111110001 .
b1010101010100100101100010101 -
#125000
b111 %
b111 +
b1111100011011011010100111111000 $
b1111100011011011010100111111000 *
b1000111101110011010000110001111 #
b1000111101110011010000110001111 )
1'
b0 &
11
b0 0
b1111 /
b100110001101011111101101001100 .
b110001001000110000011101100010 -
#130000
b1011 %
b1011 +
b10101110011111011001010001011100 $
b10101110011111011001010001011100 *
b11001111110001000101011010011111 #
b11001111110001000101011010011111 )
b111 /
b1111100011011011010100111111000 .
b1000111101110011010000110001111 -
#135000
0!
b11101001100011000110100111010010 "
b11101001100011000110100111010010 ,
b0 %
b0 +
b10100100101011100011001001001001 $
b10100100101011100011001001001001 *
b1000100110111100011011110001001 #
b1000100110111100011011110001001 )
b1011 /
b10101110011111011001010001011100 .
b11001111110001000101011010011111 -
#140000
1!
b0 "
b0 ,
b110 %
b110 +
b10101000110001111111110001010001 $
b10101000110001111111110001010001 *
b11101011111111101100000011010111 #
b11101011111111101100000011010111 )
0'
b11101001100011000110100111010010 &
01
b11101001100011000110100111010010 0
b0 /
b10100100101011100011001001001001 .
b1000100110111100011011110001001 -
#145000
0!
b11100111001111011111111111001110 "
b11100111001111011111111111001110 ,
b1000 %
b1000 +
b11100001001011001100111011000010 $
b11100001001011001100111011000010 *
b110000111010111111100001100 #
b110000111010111111100001100 )
1'
b0 &
11
b0 0
b110 /
b10101000110001111111110001010001 .
b11101011111111101100000011010111 -
#150000
1!
b0 "
b0 ,
b10 %
b10 +
b11110111100101110110100111101 $
b11110111100101110110100111101 *
b10111011100000100101101001110111 #
b10111011100000100101101001110111 )
0'
b11100111001111011111111111001110 &
01
b11100111001111011111111111001110 0
b1000 /
b11100001001011001100111011000010 .
b110000111010111111100001100 -
#155000
0!
b110110000001010000000001101100 "
b110110000001010000000001101100 ,
b1001 %
b1001 +
b110110111001011000000101101101 $
b110110111001011000000101101101 *
b10111111000001010000000001111110 #
b10111111000001010000000001111110 )
1'
b0 &
11
b0 0
b10 /
b11110111100101110110100111101 .
b10111011100000100101101001110111 -
#160000
b11100110001110010111100111001100 "
b11100110001110010111100111001100 ,
b101 %
b101 +
b11101001111010111111011011010011 $
b11101001111010111111011011010011 *
b1111110100101000111100011111 #
b1111110100101000111100011111 )
0'
b110110000001010000000001101100 &
01
b110110000001010000000001101100 0
b1001 /
b110110111001011000000101101101 .
b10111111000001010000000001111110 -
#165000
b101100000100000000100001011000 "
b101100000100000000100001011000 ,
b1001 %
b1001 +
b101101110110100101100101011011 $
b101101110110100101100101011011 *
b10111100000101001000100001111000 #
b10111100000101001000100001111000 )
b11100110001110010111100111001100 &
b11100110001110010111100111001100 0
b101 /
b11101001111010111111011011010011 .
b1111110100101000111100011111 -
#170000
b10011111111111101010111100111111 "
b10011111111111101010111100111111 ,
b1000 %
b1000 +
b10101000011001010111100101010 $
b10101000011001010111100101010 *
b10011111111100101010111000111111 #
b10011111111100101010111000111111 )
b101100000100000000100001011000 &
b101100000100000000100001011000 0
b1001 /
b101101110110100101100101011011 .
b10111100000101001000100001111000 -
#175000
1!
b0 "
b0 ,
b1100 %
b1100 +
b11000111000110100000110010001110 $
b11000111000110100000110010001110 *
b11000011001111110011100010000110 #
b11000011001111110011100010000110 )
b10011111111111101010111100111111 &
b10011111111111101010111100111111 0
b1000 /
b10101000011001010111100101010 .
b10011111111100101010111000111111 -
#180000
b11 %
b11 +
b10010011011111011011110000100110 $
b10010011011111011011110000100110 *
b1111101001101011001100111111010 #
b1111101001101011001100111111010 )
1'
b0 &
11
b0 0
b1100 /
b11000111000110100000110010001110 .
b11000011001111110011100010000110 -
#185000
b10010111100110011010100000101111 $
b10010111100110011010100000101111 *
b11010001100010111011010010100011 #
b11010001100010111011010010100011 )
b11 /
b10010011011111011011110000100110 .
b1111101001101011001100111111010 -
#190000
0!
b11111111111111111111111111111111 "
b11111111111111111111111111111111 ,
b111 %
b111 +
b100010001010010000110101000100 $
b100010001010010000110101000100 *
b10101111110110000101011001011111 #
b10101111110110000101011001011111 )
b10010111100110011010100000101111 .
b11010001100010111011010010100011 -
#195000
1!
b0 "
b0 ,
b1010 %
b1010 +
b11110011000010010001101011100110 $
b11110011000010010001101011100110 *
b11100101100110110011011011001011 #
b11100101100110110011011011001011 )
0'
b11111111111111111111111111111111 &
01
b11111111111111111111111111111111 0
b111 /
b100010001010010000110101000100 .
b10101111110110000101011001011111 -
#200000
b11110110100000101110001011101101 $
b11110110100000101110001011101101 *
b10100110011111100000100101001 #
b10100110011111100000100101001 )
1'
b0 &
11
b0 0
b1010 /
b11110011000010010001101011100110 .
b11100101100110110011011011001011 -
#205000
b1111 %
b1111 +
b11011010100010101110001010110101 $
b11011010100010101110001010110101 *
b10110010100111111011011001100101 #
b10110010100111111011011001100101 )
b11110110100000101110001011101101 .
b10100110011111100000100101001 -
#210000
0!
b1011111001000110001100010111101 "
b1011111001000110001100010111101 ,
b0 %
b0 +
b100010001100011111111101000100 $
b100010001100011111111101000100 *
b111100111100010001100101111001 #
b111100111100010001100101111001 )
b1111 /
b11011010100010101110001010110101 .
b10110010100111111011011001100101 -
#215000
1!
b0 "
b0 ,
b1110 %
b1110 +
b1010101111101101010110110101011 $
b1010101111101101010110110101011 *
b10101000010010000101100101010 #
b10101000010010000101100101010 )
0'
b1011111001000110001100010111101 &
01
b1011111001000110001100010111101 0
b0 /
b100010001100011111111101000100 .
b111100111100010001100101111001 -
#220000
b1101 %
b1101 +
b11001101010111101011110010011010 $
b11001101010111101011110010011010 *
b1101110010111011010110111011100 #
b1101110010111011010110111011100 )
1'
b0 &
11
b0 0
b1110 /
b1010101111101101010110110101011 .
b10101000010010000101100101010 -
#225000
b1110 %
b1110 +
b101011000011101110110101010110 $
b101011000011101110110101010110 *
b11100001111100010000001011000011 #
b11100001111100010000001011000011 )
b1101 /
b11001101010111101011110010011010 .
b1101110010111011010110111011100 -
#230000
b110 %
b110 +
b10000101001100010011010000001010 $
b10000101001100010011010000001010 *
b10110011110110010111011001100111 #
b10110011110110010111011001100111 )
b1110 /
b101011000011101110110101010110 .
b11100001111100010000001011000011 -
#235000
0!
b10111100110111111000111101111001 "
b10111100110111111000111101111001 ,
b1000 %
b1000 +
b111100110100011000011101111001 $
b111100110100011000011101111001 *
b10011100000011101000101000111000 #
b10011100000011101000101000111000 )
b110 /
b10000101001100010011010000001010 .
b10110011110110010111011001100111 -
#240000
1!
b0 "
b0 ,
b100 %
b100 +
b1001001110001100101110110010011 $
b1001001110001100101110110010011 *
b1001010011101001011111110010100 #
b1001010011101001011111110010100 )
0'
b10111100110111111000111101111001 &
01
b10111100110111111000111101111001 0
b1000 /
b111100110100011000011101111001 .
b10011100000011101000101000111000 -
#245000
b1101 %
b1101 +
b1101101110010110110100111011011 $
b1101101110010110110100111011011 *
b10101100101101111100101001011001 #
b10101100101101111100101001011001 )
1'
b0 &
11
b0 0
b100 /
b1001001110001100101110110010011 .
b1001010011101001011111110010100 -
#250000
b110 %
b110 +
b10110110101001000010011001101101 $
b10110110101001000010011001101101 *
b1101100101100001011011111011001 #
b1101100101100001011011111011001 )
b1101 /
b1101101110010110110100111011011 .
b10101100101101111100101001011001 -
#255000
0!
b111110001011000110010001111100 "
b111110001011000110010001111100 ,
b101 %
b101 +
b1011011000101110010110110110110 $
b1011011000101110010110110110110 *
b1100101001110110100100111001010 #
b1100101001110110100100111001010 )
b110 /
b10110110101001000010011001101101 .
b1101100101100001011011111011001 -
#260000
b11111111111111111111111111111111 "
b11111111111111111111111111111111 ,
b111 %
b111 +
b10011101001001101100000100 $
b10011101001001101100000100 *
b10100011000001110001101001000110 #
b10100011000001110001101001000110 )
0'
b111110001011000110010001111100 &
01
b111110001011000110010001111100 0
b101 /
b1011011000101110010110110110110 .
b1100101001110110100100111001010 -
#265000
b11111110111111101011111111111101 "
b11111110111111101011111111111101 ,
b1000 %
b1000 +
b11011010011011101011101010110100 $
b11011010011011101011101010110100 *
b110100100110000000011101101001 #
b110100100110000000011101101001 )
b11111111111111111111111111111111 &
b11111111111111111111111111111111 0
b111 /
b10011101001001101100000100 .
b10100011000001110001101001000110 -
#270000
1!
b0 "
b0 ,
b111 %
b111 +
b10010110100100000000010000101101 $
b10010110100100000000010000101101 *
b10100011111001101100100101000 #
b10100011111001101100100101000 )
b11111110111111101011111111111101 &
b11111110111111101011111111111101 0
b1000 /
b11011010011011101011101010110100 .
b110100100110000000011101101001 -
#275000
b1100 %
b1100 +
b10000100011101111110010000001000 $
b10000100011101111110010000001000 *
b10010111010111001001110000101110 #
b10010111010111001001110000101110 )
1'
b0 &
11
b0 0
b111 /
b10010110100100000000010000101101 .
b10100011111001101100100101000 -
#280000
b10100100111100000011100101001 $
b10100100111100000011100101001 *
b11111110101001111010011011111101 #
b11111110101001111010011011111101 )
b1100 /
b10000100011101111110010000001000 .
b10010111010111001001110000101110 -
#285000
b1101 %
b1101 +
b11101101001101000000100011011010 $
b11101101001101000000100011011010 *
b1000011001101010110011110000110 #
b1000011001101010110011110000110 )
b10100100111100000011100101001 .
b11111110101001111010011011111101 -
#290000
b11 %
b11 +
b10111000010101011100010001110000 $
b10111000010101011100010001110000 *
b110011010011101010011101100110 #
b110011010011101010011101100110 )
b1101 /
b11101101001101000000100011011010 .
b1000011001101010110011110000110 -
#295000
b1010 %
b1010 +
b101111001110101011001101011110 $
b101111001110101011001101011110 *
b1011101011100011001100110111010 #
b1011101011100011001100110111010 )
b11 /
b10111000010101011100010001110000 .
b110011010011101010011101100110 -
#300000
0!
b1000000001000000010000010000 "
b1000000001000000010000010000 ,
b1001 %
b1001 +
b10001101001001001111011000011010 $
b10001101001001001111011000011010 *
b1101010100011100000010111010101 #
b1101010100011100000010111010101 )
b1010 /
b101111001110101011001101011110 .
b1011101011100011001100110111010 -
#305000
b1100110101011101001100011001101 "
b1100110101011101001100011001101 ,
b0 %
b0 +
b1001011001001110011011110010110 $
b1001011001001110011011110010110 *
b11011100001110110000100110111 #
b11011100001110110000100110111 )
0'
b1000000001000000010000010000 &
01
b1000000001000000010000010000 0
b1001 /
b10001101001001001111011000011010 .
b1101010100011100000010111010101 -
#310000
1!
b0 "
b0 ,
b1101 %
b1101 +
b11011011010001100001101010110110 $
b11011011010001100001101010110110 *
b10011001001011001111100100110 #
b10011001001011001111100100110 )
b1100110101011101001100011001101 &
b1100110101011101001100011001101 0
b0 /
b1001011001001110011011110010110 .
b11011100001110110000100110111 -
#315000
0!
b1101111011111110101111111011110 "
b1101111011111110101111111011110 ,
b1000 %
b1000 +
b1000011011000010101011110000110 $
b1000011011000010101011110000110 *
b1101110010111110000111111011100 #
b1101110010111110000111111011100 )
1'
b0 &
11
b0 0
b1101 /
b11011011010001100001101010110110 .
b10011001001011001111100100110 -
#320000
1!
b0 "
b0 ,
b1111 %
b1111 +
b11101101100011011000000011011011 $
b11101101100011011000000011011011 *
b111111010110101001101101111110 #
b111111010110101001101101111110 )
0'
b1101111011111110101111111011110 &
01
b1101111011111110101111111011110 0
b1000 /
b1000011011000010101011110000110 .
b1101110010111110000111111011100 -
#325000
0!
b111111110001000100011001111111 "
b111111110001000100011001111111 ,
b1 %
b1 +
b11111101001010001110010011111010 $
b11111101001010001110010011111010 *
b111100111011010010101101111001 #
b111100111011010010101101111001 )
1'
b0 &
11
b0 0
b1111 /
b11101101100011011000000011011011 .
b111111010110101001101101111110 -
#330000
1!
b0 "
b0 ,
b110 %
b110 +
b11010000111101010111100010100001 $
b11010000111101010111100010100001 *
b1011100101000000100100010111 #
b1011100101000000100100010111 )
0'
b111111110001000100011001111111 &
01
b111111110001000100011001111111 0
b1 /
b11111101001010001110010011111010 .
b111100111011010010101101111001 -
#335000
0!
b11010010111011111100111110100101 "
b11010010111011111100111110100101 ,
b101 %
b101 +
b1111010100011000101100111110101 $
b1111010100011000101100111110101 *
b10101000011000111001011001010000 #
b10101000011000111001011001010000 )
1'
b0 &
11
b0 0
b110 /
b11010000111101010111100010100001 .
b1011100101000000100100010111 -
#340000
b11110100001010111111111111101000 "
b11110100001010111111111111101000 ,
b1100000101100010111010111000001 $
b1100000101100010111010111000001 *
b10010100100110101000101000101001 #
b10010100100110101000101000101001 )
0'
b11010010111011111100111110100101 &
01
b11010010111011111100111110100101 0
b101 /
b1111010100011000101100111110101 .
b10101000011000111001011001010000 -
#345000
b1 "
b1 ,
b11 %
b11 +
b100101101100100111101101001011 $
b100101101100100111101101001011 *
b11001100000000011011010010011000 #
b11001100000000011011010010011000 )
b11110100001010111111111111101000 &
b11110100001010111111111111101000 0
b1100000101100010111010111000001 .
b10010100100110101000101000101001 -
#350000
1!
b0 "
b0 ,
b1110 %
b1110 +
b11000101010100000001011010001010 $
b11000101010100000001011010001010 *
b11110110001000101110011011101100 #
b11110110001000101110011011101100 )
b1 &
b1 0
b11 /
b100101101100100111101101001011 .
b11001100000000011011010010011000 -
#355000
0!
b1111111101011001000001011111111 "
b1111111101011001000001011111111 ,
b1 %
b1 +
b1010100100111101111110110101001 $
b1010100100111101111110110101001 *
b11010100010010111000000010101000 #
b11010100010010111000000010101000 )
1'
b0 &
11
b0 0
b1110 /
b11000101010100000001011010001010 .
b11110110001000101110011011101100 -
#360000
1!
b0 "
b0 ,
b1111 %
b1111 +
b11110011001101000110011011100110 $
b11110011001101000110011011100110 *
b111000010111011100100001110 #
b111000010111011100100001110 )
0'
b1111111101011001000001011111111 &
01
b1111111101011001000001011111111 0
b1 /
b1010100100111101111110110101001 .
b11010100010010111000000010101000 -
#365000
b1101 %
b1101 +
b10101010110100001110100101010 $
b10101010110100001110100101010 *
b10101001011111011010100101010 #
b10101001011111011010100101010 )
1'
b0 &
11
b0 0
b1111 /
b11110011001101000110011011100110 .
b111000010111011100100001110 -
#370000
0!
b1100011001011110011000011000 "
b1100011001011110011000011000 ,
b1001 %
b1001 +
b10011100011011011110011000111000 $
b10011100011011011110011000111000 *
b1001111011101011111111110011110 #
b1001111011101011111111110011110 )
b1101 /
b10101010110100001110100101010 .
b10101001011111011010100101010 -
#375000
b1 "
b1 ,
b11 %
b11 +
b1100101001000110100010111001010 $
b1100101001000110100010111001010 *
b1100100011001001110001111001000 #
b1100100011001001110001111001000 )
0'
b1100011001011110011000011000 &
01
b1100011001011110011000011000 0
b1001 /
b10011100011011011110011000111000 .
b1001111011101011111111110011110 -
#380000
1!
b0 "
b0 ,
b110 %
b110 +
b11100011101101111010111011000111 $
b11100011101101111010111011000111 *
b110101101000001100100101101011 #
b110101101000001100100101101011 )
b1 &
b1 0
b11 /
b1100101001000110100010111001010 .
b1100100011001001110001111001000 -
#385000
0!
b1000000000001001000100110000000 "
b1000000000001001000100110000000 ,
b1001 %
b1001 +
b1100010000101101010101111000100 $
b1100010000101101010101111000100 *
b1011101000001011001110110111010 #
b1011101000001011001110110111010 )
1'
b0 &
11
b0 0
b110 /
b11100011101101111010111011000111 .
b110101101000001100100101101011 -
#390000
1!
b0 "
b0 ,
b1111 %
b1111 +
b11011010001001101001101010110100 $
b11011010001001101001101010110100 *
b1001001001011111101001110010010 #
b1001001001011111101001110010010 )
0'
b1000000000001001000100110000000 &
01
b1000000000001001000100110000000 0
b1001 /
b1100010000101101010101111000100 .
b1011101000001011001110110111010 -
#395000
b10 %
b10 +
b1111101011011011111010111111010 $
b1111101011011011111010111111010 *
b11000011001100111001000010000110 #
b11000011001100111001000010000110 )
1'
b0 &
11
b0 0
b1111 /
b11011010001001101001101010110100 .
b1001001001011111101001110010010 -
